setup.py
silvermirror/__init__.py
silvermirror/config.py
silvermirror/hg.py
silvermirror/interface.py
silvermirror/unify.py
silvermirror/unison.py
silvermirror/utils.py
silvermirror.egg-info/PKG-INFO
silvermirror.egg-info/SOURCES.txt
silvermirror.egg-info/dependency_links.txt
silvermirror.egg-info/entry_points.txt
silvermirror.egg-info/not-zip-safe
silvermirror.egg-info/requires.txt
silvermirror.egg-info/top_level.txt
test/test_unify.py